agpytesting/__init__.py
agpytesting/algorithm.py
agpytesting/configuration.py
agpytesting/entrypoint.py
agpytesting/environment.py
agpytesting/geoimage.py
agpytesting/geometries.py
agpytesting/lasfile.py
agpytesting-0.0.8.dist-info/LICENSE
agpytesting-0.0.8.dist-info/METADATA
agpytesting-0.0.8.dist-info/WHEEL
agpytesting-0.0.8.dist-info/top_level.txt
agpytesting-0.0.8.dist-info/RECORD
